avulto/__init__.py
avulto/ast/__init__.py
avulto/ast/__init__.pyi
avulto/avulto.cpython-313t-x86_64-linux-musl.so
avulto/avulto.pyi
avulto/helpers.py
avulto/py.typed
avulto-0.2.6.dist-info/METADATA
avulto-0.2.6.dist-info/WHEEL
avulto-0.2.6.dist-info/licenses/LICENSE
avulto.libs/libgcc_s-6d2d9dc8.so.1
avulto-0.2.6.dist-info/RECORD
