Metadata-Version: 2.4
Name: avulto
Version: 0.2.6
License-File: LICENSE
Summary: A Python API for working with BYOND projects.
Author-email: Warriorstar Orion <orion@snowfrost.garden>
Requires-Python: >=3.12
Project-URL: repository, https://github.com/warriorstar-orion/avulto
